imgio/__init__.py
imgio/imgio.py
imgio/pfm.py
imgio/pnm.py
imgio/version.py
imgio/test-images/GrayRampsDiagonal.exr
imgio/test-images/landscape_1.jpg
imgio/test-images/landscape_2.jpg
imgio/test-images/landscape_3.jpg
imgio/test-images/landscape_4.jpg
imgio/test-images/landscape_5.jpg
imgio/test-images/landscape_6.jpg
imgio/test-images/landscape_7.jpg
imgio/test-images/landscape_8.jpg
imgio/test-images/portrait_1.jpg
imgio/test-images/portrait_2.jpg
imgio/test-images/portrait_3.jpg
imgio/test-images/portrait_4.jpg
imgio/test-images/portrait_5.jpg
imgio/test-images/portrait_6.jpg
imgio/test-images/portrait_7.jpg
imgio/test-images/portrait_8.jpg
imgio-1.6.0.dist-info/METADATA
imgio-1.6.0.dist-info/WHEEL
imgio-1.6.0.dist-info/licenses/LICENSE
imgio-1.6.0.dist-info/RECORD
