Metadata-Version: 2.3
Name: imgio
Version: 1.6.0
Summary: Easy image reading & writing
Project-URL: Homepage, http://github.com/toaarnio/imgio
Author-email: Tomi Aarnio <tomi.p.aarnio@gmail.com>
License: MIT License
License-File: LICENSE
Classifier: License :: OSI Approved :: MIT License
Classifier: Operating System :: OS Independent
Classifier: Programming Language :: Python :: 3
Requires-Python: >=3.10
Requires-Dist: imageio
Requires-Dist: numpy
Requires-Dist: openexr
Requires-Dist: pyexr
